rustflow-0.1.0.dist-info/METADATA
rustflow-0.1.0.dist-info/WHEEL
rustflow/__init__.py
rustflow/reach/__init__.py
rustflow/rustflow.cpython-312-darwin.so
rustflow-0.1.0.dist-info/RECORD
