Metadata-Version: 2.4
Name: rustflow
Version: 0.1.0
Classifier: Programming Language :: Rust
Classifier: Programming Language :: Python :: Implementation :: CPython
Classifier: Programming Language :: Python :: Implementation :: PyPy
Requires-Dist: pandas>=2.2.3
Requires-Python: >=3.12
